server/__init__.py
server/server.py
server/server_gui.py
server/server_resource.py
server/server_storage.py
my_messanger_server-0.0.0.dist-info/METADATA
my_messanger_server-0.0.0.dist-info/WHEEL
my_messanger_server-0.0.0.dist-info/top_level.txt
my_messanger_server-0.0.0.dist-info/RECORD
